imline/__init__.py
imline/__main__.py
imline/db_fetching.py
imline/delanuay2D.py
imline/downloading.py
imline/logging.py
imline/mapping.py
imline/multiplication.py
imline/object_detection.py
imline/presentation.py
imline-0.0.31.dist-info/LICENSE
imline-0.0.31.dist-info/METADATA
imline-0.0.31.dist-info/WHEEL
imline-0.0.31.dist-info/entry_points.txt
imline-0.0.31.dist-info/top_level.txt
imline-0.0.31.dist-info/RECORD
