Metadata-Version: 2.1
Name: imline
Version: 0.0.31
Summary: imline is key point marker and angular map creator on a face
Home-page: https://github.com/MCYBA/ImLine
Author: Cem Baybars GÜÇLÜ
Author-email: cem.baybars@gmail.com
License: MIT
Keywords: image processing computer vision face mapping key-points
Platform: UNKNOWN
Classifier: Development Status :: 1 - Planning
Classifier: Intended Audience :: Science/Research
Classifier: Topic :: Scientific/Engineering :: Visualization
Classifier: License :: OSI Approved :: MIT License
Classifier: Natural Language :: English
Classifier: Operating System :: POSIX :: Linux
Classifier: Programming Language :: Python :: 3 :: Only
Requires-Dist: tinydb (==4.1.1)
Requires-Dist: numpy
Requires-Dist: multipledispatch
Requires-Dist: psutil
Requires-Dist: gitpython
Requires-Dist: imutils
Requires-Dist: google-images-download
Requires-Dist: stasm
Provides-Extra: optionals
Requires-Dist: flake8 ; extra == 'optionals'
Requires-Dist: sphinx ; extra == 'optionals'
Requires-Dist: sphinx-rtd-theme ; extra == 'optionals'
Requires-Dist: recommonmark ; extra == 'optionals'
Requires-Dist: docutils ; extra == 'optionals'
Requires-Dist: m2r ; extra == 'optionals'
Requires-Dist: pytest ; extra == 'optionals'
Requires-Dist: pytest-cov (==2.6.1) ; extra == 'optionals'
Requires-Dist: coveralls (==1.8.2) ; extra == 'optionals'
